latex2bundle/__init__.py
latex2bundle/__main__.py
latex2bundle/cli.py
latex2bundle/combine_bib.py
latex2bundle-0.1.3.dist-info/licenses/LICENSE
latex2bundle-0.1.3.dist-info/METADATA
latex2bundle-0.1.3.dist-info/WHEEL
latex2bundle-0.1.3.dist-info/entry_points.txt
latex2bundle-0.1.3.dist-info/top_level.txt
latex2bundle-0.1.3.dist-info/RECORD
