Metadata-Version: 2.4
Name: latex2bundle
Version: 0.1.3
Summary: Bundle a LaTeX project (resolve input includes, collect figures and auxiliary files) into a zip archive.
License: MIT License
Project-URL: Homepage, https://github.com/bacox/latex-2-bundle
Keywords: latex,bundle,zip
Classifier: Programming Language :: Python :: 3
Classifier: License :: OSI Approved :: MIT License
Classifier: Operating System :: OS Independent
Requires-Python: >=3.8
License-File: LICENSE
Dynamic: license-file
